ModelBenchmark/ModelBenchmarker.py
ModelBenchmark/__init__.py
infbench-0.0.1.dist-info/LICENSE
infbench-0.0.1.dist-info/METADATA
infbench-0.0.1.dist-info/WHEEL
infbench-0.0.1.dist-info/top_level.txt
infbench-0.0.1.dist-info/RECORD
