Metadata-Version: 2.1
Name: infbench
Version: 0.0.1
Summary: Tool for benchmarking inference.
Home-page: UNKNOWN
Author: Radoslav Ralev)
Author-email: radoslav.ralev@tum.de
License: UNKNOWN
Keywords: python,deep learning,benchmark,inference,openvino,sockets
Platform: UNKNOWN
Classifier: Development Status :: 1 - Planning
Classifier: Intended Audience :: Developers
Classifier: Programming Language :: Python :: 3
Classifier: Operating System :: Unix
Classifier: Operating System :: MacOS :: MacOS X
Classifier: Operating System :: Microsoft :: Windows
License-File: LICENSE
